wirepusher/__init__.py
wirepusher-0.0.1.dist-info/LICENSE
wirepusher-0.0.1.dist-info/METADATA
wirepusher-0.0.1.dist-info/WHEEL
wirepusher-0.0.1.dist-info/top_level.txt
wirepusher-0.0.1.dist-info/RECORD
