Metadata-Version: 2.1
Name: wirepusher
Version: 0.0.1
Summary: API client for the Wirepusher notification app for Android.
Author-email: Sentynel <wirepusher@sentynel.com>
Project-URL: Repository, https://github.com/Sentynel/wirepusher.git
Classifier: Development Status :: 4 - Beta
Classifier: License :: OSI Approved :: MIT License
Classifier: Programming Language :: Python :: 3
Requires-Python: >=3.6
License-File: LICENSE
Requires-Dist: requests
Requires-Dist: pycryptodome
